CHANGES.txt
README.txt
bootstrap.py
buildout.cfg
setup.py
cfgs/plone-4.cfg
docs/LICENSE.GPL
docs/LICENSE.txt
src/collective/__init__.py
src/collective.ATClamAV.egg-info/PKG-INFO
src/collective.ATClamAV.egg-info/SOURCES.txt
src/collective.ATClamAV.egg-info/dependency_links.txt
src/collective.ATClamAV.egg-info/entry_points.txt
src/collective.ATClamAV.egg-info/namespace_packages.txt
src/collective.ATClamAV.egg-info/not-zip-safe
src/collective.ATClamAV.egg-info/requires.txt
src/collective.ATClamAV.egg-info/top_level.txt
src/collective/ATClamAV/__init__.py
src/collective/ATClamAV/configure.zcml
src/collective/ATClamAV/interfaces.py
src/collective/ATClamAV/scanner.py
src/collective/ATClamAV/schema.py
src/collective/ATClamAV/testing.py
src/collective/ATClamAV/validator.py
src/collective/ATClamAV/browser/__init__.py
src/collective/ATClamAV/browser/clamav.ico
src/collective/ATClamAV/browser/configure.zcml
src/collective/ATClamAV/browser/settings.py
src/collective/ATClamAV/profiles/default/controlpanel.xml
src/collective/ATClamAV/profiles/default/metadata.xml
src/collective/ATClamAV/profiles/default/propertiestool.xml
src/collective/ATClamAV/tests/__init__.py
src/collective/ATClamAV/tests/base.py
src/collective/ATClamAV/tests/test_integration.py
src/collective/ATClamAV/tests/test_scanner.py
src/collective/ATClamAV/tests/data/image.png