Metadata-Version: 1.0
Name: collective.ATClamAV
Version: 1.0
Summary: Provides ClamAV antivirus integration for Archetypes based content types
Home-page: http://pypi.python.org/pypi/collective.ATClamAV
Author: Yiorgis Gozadinos
Author-email: ggozad@jarn.com
License: GPL
Keywords: plone antivirus archetypes
Platform: Any
Classifier: Environment :: Web Environment
Classifier: Framework :: Plone
Classifier: Intended Audience :: Developers
Classifier: License :: OSI Approved :: GNU General Public License (GPL)
Classifier: Operating System :: OS Independent
Classifier: Programming Language :: Python
